betfairstreamer/__init__.py
betfairstreamer/api_client.py
betfairstreamer/py.typed
betfairstreamer/utils.py
betfairstreamer/helpers/__init__.py
betfairstreamer/helpers/stream_helpers.py
betfairstreamer/models/__init__.py
betfairstreamer/models/betfair_api.py
betfairstreamer/models/betfair_api_extensions.py
betfairstreamer/models/market_book.py
betfairstreamer/models/market_cache.py
betfairstreamer/models/order_book.py
betfairstreamer/models/order_cache.py
betfairstreamer/stream/__init__.py
betfairstreamer/stream/betfair_async_connection.py
betfairstreamer/stream/betfair_connection.py
betfairstreamer/stream/betfair_connection_pool.py
betfairstreamer/stream/pipeline_connection.py
betfairstreamer/stream/protocols.py
betfairstreamer/stream/stream_parser.py
betfairstreamer-0.8.0.dist-info/LICENSE
betfairstreamer-0.8.0.dist-info/METADATA
betfairstreamer-0.8.0.dist-info/WHEEL
betfairstreamer-0.8.0.dist-info/entry_points.txt
betfairstreamer-0.8.0.dist-info/top_level.txt
betfairstreamer-0.8.0.dist-info/RECORD
