Metadata-Version: 2.1
Name: betfairstreamer
Version: 0.8.0
Summary: Betfair Exchange Stream API wrapper
Home-page: https://github.com/almenjonatan/betfairstreamer.git
Author: Jonatan Almen
Author-email: almen.jonatan@gmail.com
License: UNKNOWN
Platform: UNKNOWN
Classifier: Programming Language :: Python :: 3
Classifier: License :: OSI Approved :: MIT License
Requires-Python: >=3.8.0
Requires-Dist: numpy
Requires-Dist: ciso8601
Requires-Dist: attrs
Requires-Dist: pytz
Requires-Dist: zmq
Requires-Dist: requests
